[
  {
    "id": "vendor_1",
    "name": "Auntie Comfort's Fruits",
    "category": "fruit",
    "location": "Adukrom Market",
    "hours": "Mon-Sat, 7am-6pm",
    "contact": "+233 24 111 2222",
    "whatsapp": "233241112222",
    "speciality": "Fresh pineapples and mangoes",
    "priceRange": "GHS 5-20",
    "rating": 4.9,
    "description": "The freshest fruits around! Auntie Comfort get the sweetest pineapple for here!",
    "recommendations": 45
  },
  {
    "id": "vendor_2",
    "name": "Kojo's Tailoring Shop",
    "category": "tailor",
    "location": "Berekuso Junction",
    "hours": "Mon-Fri, 8am-7pm",
    "contact": "+233 20 222 3333",
    "whatsapp": "233202223333",
    "speciality": "African print designs, kaftan",
    "priceRange": "GHS 50-300",
    "rating": 4.8,
    "description": "Expert tailor with over 15 years experience. Your kaba and slit go fit you well!",
    "recommendations": 38
  },
  {
    "id": "vendor_3",
    "name": "Sharp Cuts Barbershop",
    "category": "barber",
    "location": "Near Ashesi Gate",
    "hours": "Daily, 9am-9pm",
    "contact": "+233 27 333 4444",
    "whatsapp": "233273334444",
    "speciality": "Fades, designs, beards",
    "priceRange": "GHS 10-30",
    "rating": 5.0,
    "description": "Your favorite campus barber! Clean cuts, fresh fades. We go make you sharp!",
    "recommendations": 67
  },
  {
    "id": "vendor_4",
    "name": "Mama Fati's Kitchen",
    "category": "food",
    "location": "Peduase Lodge",
    "hours": "Daily, 11am-9pm",
    "contact": "+233 55 444 5555",
    "whatsapp": "233554445555",
    "speciality": "Jollof rice, waakye, banku",
    "priceRange": "GHS 15-35",
    "rating": 4.9,
    "description": "Best jollof in town! Mama Fati's food dey always hit different. Come chop!",
    "recommendations": 89
  },
  {
    "id": "vendor_5",
    "name": "Sister Gloria's Hair Salon",
    "category": "barber",
    "location": "Adukrom Center",
    "hours": "Tue-Sun, 8am-8pm",
    "contact": "+233 24 555 6666",
    "whatsapp": "233245556666",
    "speciality": "Braids, weaves, natural hair care",
    "priceRange": "GHS 30-150",
    "rating": 4.7,
    "description": "Professional hair stylist. All styles available - from Ghana weaving to box braids!",
    "recommendations": 52
  },
  {
    "id": "vendor_6",
    "name": "Uncle Ben's Fruit Stand",
    "category": "fruit",
    "location": "Berekuso Main Road",
    "hours": "Daily, 6am-7pm",
    "contact": "+233 20 666 7777",
    "whatsapp": "233206667777",
    "speciality": "Watermelons, oranges, pawpaw",
    "priceRange": "GHS 3-25",
    "rating": 4.6,
    "description": "Fresh fruits delivered daily from the farm. Uncle Ben dey give discount for students!",
    "recommendations": 41
  },
  {
    "id": "vendor_7",
    "name": "Afua's Seamstress Corner",
    "category": "tailor",
    "location": "Near Police Station, Adukrom",
    "hours": "Mon-Sat, 9am-6pm",
    "contact": "+233 27 777 8888",
    "whatsapp": "233277778888",
    "speciality": "Wedding dresses, casual wear",
    "priceRange": "GHS 80-400",
    "rating": 4.8,
    "description": "Beautiful designs at affordable prices. Afua sabi sew paaa! Your dress go sweet!",
    "recommendations": 36
  },
  {
    "id": "vendor_8",
    "name": "Chop Bar Express",
    "category": "food",
    "location": "Berekuso Junction",
    "hours": "Mon-Sat, 10am-8pm",
    "contact": "+233 50 888 9999",
    "whatsapp": "233508889999",
    "speciality": "Fast delivery, local dishes",
    "priceRange": "GHS 12-30",
    "rating": 4.5,
    "description": "Quick delivery to campus! Call for fufu, banku, kenkey. We move fast!",
    "recommendations": 73
  }
]
